setup.cfg
setup.py
neotiles/__init__.py
neotiles/pixelcolor.py
neotiles/tile.py
neotiles/tilemanager.py
neotiles.egg-info/PKG-INFO
neotiles.egg-info/SOURCES.txt
neotiles.egg-info/dependency_links.txt
neotiles.egg-info/requires.txt
neotiles.egg-info/top_level.txt
neotiles/exceptions/__init__.py
neotiles/matrixes/__init__.py