Metadata-Version: 1.0
Name: neotiles
Version: 0.4.0
Summary: Treat a neopixel or RGB matrix as a collection of separate tiles
Home-page: https://github.com/mjoblin/neotiles
Author: Mike Joblin
Author-email: mike@tastymoss.com
License: MIT
Platform: UNKNOWN
